[
  {
    "id": "Ascidiacea",
    "className": "Ascidiacea",
    "species": [
      {
        "id": 1,
        "slug": "ascidia",
        "name": "Ascidia",
        "scientificName": "Sea squirt",
        "image": "https://res.cloudinary.com/duibfmcw1/image/upload/v1767894433/Ascidia_jhgqzv.png",
        "path": "/zoohub/chordata/ascidia"
      },
      {
        "id": 2,
        "slug": "herdmania",
        "name": "Herdmania",
        "scientificName": "Red sea squirt",
        "image": "https://res.cloudinary.com/duibfmcw1/image/upload/v1767894447/Herdmania_ecxear.png",
        "path": "/zoohub/chordata/herdmania"
      }
    ]
  },
  {
    "id": "Thaliacea",
    "className": "Thaliacea",
    "species": [
      {
        "id": 3,
        "slug": "salpa",
        "name": "Salpa",
        "scientificName": "Salp",
        "image": "https://res.cloudinary.com/duibfmcw1/image/upload/v1767895302/Salpa_v6xxui.png",
        "path": "/zoohub/chordata/salpa"
      },
      {
        "id": 4,
        "slug": "doliolum",
        "name": "Doliolum",
        "scientificName": "Doliolid",
        "image": "https://res.cloudinary.com/duibfmcw1/image/upload/v1767895311/Doliolum_kcjpas.png",
        "path": "/zoohub/chordata/doliolum"
      },
      {
        "id": 5,
        "slug": "pyrosoma",
        "name": "Pyrosoma",
        "scientificName": "Fire body",
        "image": "https://res.cloudinary.com/duibfmcw1/image/upload/v1767895306/Pyrosoma_xupmt9.png",
        "path": "/zoohub/chordata/pyrosoma"
      }
    ]
  },
  {
    "id": "Leptocardii",
    "className": "Leptocardii",
    "species": [
      {
        "id": 6,
        "slug": "branchiostoma",
        "name": "Branchiostoma lanceolatum",
        "scientificName": "Lancelet / Amphioxus",
        "image": "https://res.cloudinary.com/duibfmcw1/image/upload/v1767895339/Branchiostoma_lanceolatum_lnmage.png",
        "path": "/zoohub/chordata/branchiostoma"
      }
    ]
  },
  {
    "id": "cyclostomata",
    "className": "Cyclostomata",
    "species": [
      {
        "id": 7,
        "slug": "petromyzon",
        "name": "Petromyzon marinus",
        "scientificName": "Sea lamprey",
        "image": "https://res.cloudinary.com/duibfmcw1/image/upload/v1767895415/Petromyzon_marinus_smue6p.png",
        "path": "/zoohub/chordata/petromyzon"
      },
      {
        "id": 8,
        "slug": "myxine",
        "name": "Myxine glutinosa",
        "scientificName": "Hagfish/slime eel",
        "image": "https://res.cloudinary.com/duibfmcw1/image/upload/v1767895410/myxine_glutinosa_vyqwnl.png ",
        "path": "/zoohub/chordata/myxine"
      }
    ]
  },
  {
    "id": "chondrichthyes",
    "className": "Chondrichthyes",
    "species": [
      {
        "id": 9,
        "slug": "scoliodon",
        "name": "Scoliodon laticaudus",
        "scientificName": "Dogfish / Spadenose shark",
        "image": "https://res.cloudinary.com/duibfmcw1/image/upload/v1770196659/Scoliodon_laticaudus_onqoyb.png",
        "path": "/zoohub/chordata/scoliodon"
      },
      {
        "id": 10,
        "slug": "pristis",
        "name": "Pristis",
        "scientificName": "Sawfish",
        "image": "https://res.cloudinary.com/duibfmcw1/image/upload/v1770196645/Pristis_hv29co.png",
        "path": "/zoohub/chordata/pristis"
      },
      {
        "id": 11,
        "slug": "trygon",
        "name": "Trygon",
        "scientificName": "Stingray",
        "image": "https://res.cloudinary.com/duibfmcw1/image/upload/v1770196672/Trygon_jv0e3i.png",
        "path": "/zoohub/chordata/trygon"
      },
      {
        "id": 12,
        "slug": "torpedo",
        "name": "Torpedo",
        "scientificName": "Electric ray",
        "image": "https://res.cloudinary.com/duibfmcw1/image/upload/v1770196667/Torpedo_jk0rwb.png",
        "path": "/zoohub/chordata/torpedo"
      },
      {
        "id": 13,
        "slug": "carcharodon",
        "name": "Carcharodon carcharias",
        "scientificName": "Great white shark",
        "image": "https://res.cloudinary.com/duibfmcw1/image/upload/v1770196618/Carcharodon_carcharias_snql93.png",
        "path": "/zoohub/chordata/carcharodon"
      }
    ]
  },
  {
    "id": "Osteichthyes",
    "className": "Osteichthyes",
    "species": [
      {
        "id": 14,
        "slug": "exocoetus",
        "name": "Exocoetus",
        "scientificName": "Flying fish",
        "image": "https://res.cloudinary.com/duibfmcw1/image/upload/v1770197387/Exocoetus_kvnttp.png",
        "path": "/zoohub/chordata/exocoetus"
      },
      {
        "id": 15,
        "slug": "hippocampus",
        "name": "Hippocampus",
        "scientificName": "Seahorse",
        "image": "https://res.cloudinary.com/duibfmcw1/image/upload/v1770197390/Hippocampus_r4zr6o.png",
        "path": "/zoohub/chordata/hippocampus"
      },
      {
        "id": 16,
        "slug": "labeo",
        "name": "Labeo rohita",
        "scientificName": "Rohu",
        "image": "https://res.cloudinary.com/duibfmcw1/image/upload/v1770197393/Labeo_rohita_g6zyn0.png",
        "path": "/zoohub/chordata/labeo"
      },
      {
        "id": 17,
        "slug": "catla",
        "name": "Catla catla",
        "scientificName": "Catla",
        "image": "https://res.cloudinary.com/duibfmcw1/image/upload/v1770197366/Catla_catla_algwyr.png",
        "path": "/zoohub/chordata/catla"
      },
      {
        "id": 18,
        "slug": "clarias",
        "name": "Clarias batrachus",
        "scientificName": "Magur",
        "image": "https://res.cloudinary.com/duibfmcw1/image/upload/v1770197380/Clarias_batrachus_toqsqe.png",
        "path": "/zoohub/chordata/clarias"
      },
      {
        "id": 19,
        "slug": "echeneis",
        "name": "Echeneis",
        "scientificName": "Sucker fish / Remora",
        "image": "https://res.cloudinary.com/duibfmcw1/image/upload/v1770197384/Echeneis_rndj1u.png",
        "path": "/zoohub/chordata/echeneis"
      },
      {
        "id": 20,
        "slug": "betta",
        "name": "Betta splendens",
        "scientificName": "Fighter fish",
        "image": "https://res.cloudinary.com/duibfmcw1/image/upload/v1770197339/Betta_splendens_r5yyew.png",
        "path": "/zoohub/chordata/betta"
      },
      {
        "id": 21,
        "slug": "pterophyllum",
        "name": "Pterophyllum scalare",
        "scientificName": "Angel fish",
        "image": "https://res.cloudinary.com/duibfmcw1/image/upload/v1770197404/Pterophyllum_scalare_qfqoqn.png",
        "path": "/zoohub/chordata/pterophyllum"
      },{
        "id": 22,
        "slug": "latimeria",
        "name": "Latimeria chalumnae",
        "scientificName": "Coelacanth",
        "image": "https://res.cloudinary.com/duibfmcw1/image/upload/v1770197400/Latimeria_chalumnae_zlrae2.png",
        "path": "/zoohub/chordata/latimeria"
      },
      {
        "id": 23,
        "slug": "protopterus",
        "name": "Protopterus annectens",
        "scientificName": "African lungfish",
        "image": "https://res.cloudinary.com/duibfmcw1/image/upload/v1770197397/Protopterus_annectens_fc1lqr.png",
        "path": "/zoohub/chordata/protopterus"
      }
    ]
  },

  {
    "id": "amphibia",
    "className": "Amphibia",
    "species": [
      {
        "id": 24,
        "slug": "bufo",
        "name": "Bufo",
        "scientificName": "Toad",
        "image": "https://res.cloudinary.com/duibfmcw1/image/upload/v1770197529/Bufo_iky9ot.png",
        "path": "/zoohub/chordata/bufo"
      },
      {
        "id": 25,
        "slug": "alytes",
        "name": "Alytes",
        "scientificName": "Midwife toad",
        "image": "https://res.cloudinary.com/duibfmcw1/image/upload/v1770197518/Alytes_oezmlf.png",
        "path": "/zoohub/chordata/alytes"
      },
      {
        "id": 26,
        "slug": "hyla",
        "name": "Hyla",
        "scientificName": "Tree frog",
        "image": "https://res.cloudinary.com/duibfmcw1/image/upload/v1770197544/Hyla_lbmzja.png",
        "path": "/zoohub/chordata/hyla"
      },
      {
        "id": 27,
        "slug": "rhacophorus",
        "name": "Rhacophorus",
        "scientificName": "Flying frog",
        "image": "https://res.cloudinary.com/duibfmcw1/image/upload/v1770197754/Rhacophorus_paaoef.png",
        "path": "/zoohub/chordata/rhacophorus"
      },
      {
        "id": 28,
        "slug": "rana",
        "name": "Rana",
        "scientificName": "Frog",
        "image": "https://res.cloudinary.com/duibfmcw1/image/upload/v1770197751/Rana_dpyid8.png",
        "path": "/zoohub/chordata/rana"
      },
      {
        "id": 29,
        "slug": "necturus",
        "name": "Necturus maculosus",
        "scientificName": "Mudpuppy",
        "image": "https://res.cloudinary.com/duibfmcw1/image/upload/v1770197748/Necturus_maculosus_bymsxk.png",
        "path": "/zoohub/chordata/necturus"
      },
      {
        "id": 30,
        "slug": "ambystoma",
        "name": "Ambystoma tigrinum",
        "scientificName": "Tiger salamander",
        "image": "https://res.cloudinary.com/duibfmcw1/image/upload/v1770197526/Ambystoma_tigrinum_ltgewv.png",
        "path": "/zoohub/chordata/ambystoma"
      },
      {
        "id": 31,
        "slug": "salamandra",
        "name": "Salamandra",
        "scientificName": "Fire salamander",
        "image": "https://res.cloudinary.com/duibfmcw1/image/upload/v1770197757/Salamandra_km1ahw.png",
        "path": "/zoohub/chordata/salamandra"
      },
      {
        "id": 32,
        "slug": "ichthyophis",
        "name": "Ichthyophis",
        "scientificName": "Caecilian",
        "image": "https://res.cloudinary.com/duibfmcw1/image/upload/v1770197557/Ichthyophis_oqw4wr.png",
        "path": "/zoohub/chordata/ichthyophis"
      }
    ]
  },
  {
    "id": "reptilia",
    "className": "Reptilia",
    "species": [
      {
        "id": 33,
        "slug": "hemidactylus",
        "name": "Hemidactylus",
        "scientificName": "House lizard / Gecko",
        "image": "https://res.cloudinary.com/duibfmcw1/image/upload/v1770197883/Hemidactylus_bqzpvf.png",
        "path": "/zoohub/chordata/hemidactylus"
      },
      {
        "id": 34,
        "slug": "calotes",
        "name": "Calotes",
        "scientificName": "Garden lizard",
        "image": "https://res.cloudinary.com/duibfmcw1/image/upload/v1770197855/Calotes_g8mz9s.png",
        "path": "/zoohub/chordata/calotes"
      },
      {
        "id": 35,
        "slug": "draco",
        "name": "Draco",
        "scientificName": "Flying lizard",
        "image": "https://res.cloudinary.com/duibfmcw1/image/upload/v1770197872/Draco_amkrks.png",
        "path": "/zoohub/chordata/draco"
      },
      {
        "id": 36,
        "slug": "chamaeleon",
        "name": "Chamaeleon",
        "scientificName": "Chameleon",
        "image": "https://res.cloudinary.com/duibfmcw1/image/upload/v1770197862/Chamaeleon_gtimfs.png",
        "path": "/zoohub/chordata/chamaeleon"
      },
      {
        "id": 37,
        "slug": "phrynosoma",
        "name": "Phrynosoma",
        "scientificName": "Horned lizard",
        "image": "https://res.cloudinary.com/duibfmcw1/image/upload/v1770197938/Phrynosoma_s02hd1.png",
        "path": "/zoohub/chordata/phrynosoma"
      },
      {
        "id": 38,
        "slug": "varanus",
        "name": "Varanus",
        "scientificName": "Monitor lizard",
        "image": "https://res.cloudinary.com/duibfmcw1/image/upload/v1770198076/Varanus_npexhs.png",
        "path": "/zoohub/chordata/varanus"
      },
      {
        "id": 39,
        "slug": "sphenodon_punctatum",
        "name": "Sphenodon punctatum",
        "scientificName": "Tuatara",
        "image": "https://res.cloudinary.com/duibfmcw1/image/upload/v1770198041/Sphenodon_punctatum_bx838s.png",
        "path": "/zoohub/chordata/sphenodon_punctatum"
      },
      {
        "id": 40,
        "slug": "chelone",
        "name": "Chelone",
        "scientificName": "Sea turtle",
        "image": "https://res.cloudinary.com/duibfmcw1/image/upload/v1770197859/Chelone_ea4fpo.png",
        "path": "/zoohub/chordata/chelone"
      },
      {
        "id": 41,
        "slug": "testudo",
        "name": "Testudo",
        "scientificName": "Tortoise",
        "image": "https://res.cloudinary.com/duibfmcw1/image/upload/v1770198055/Testudo_p5k79t.png",
        "path": "/zoohub/chordata/testudo"
      },
      {
        "id": 42,
        "slug": "naja_naja",
        "name": "Naja naja",
        "scientificName": "Indian cobra",
        "image": "https://res.cloudinary.com/duibfmcw1/image/upload/v1770197893/Naja_naja_zlcckg.png",
        "path": "/zoohub/chordata/naja_naja"
      },
      {
        "id": 43,
        "slug": "vipera_russelli",
        "name": "Vipera russelli",
        "scientificName": "Russell's viper",
        "image": "https://res.cloudinary.com/duibfmcw1/image/upload/v1770198072/Vipera_russelli_kbzx1t.png",
        "path": "/zoohub/chordata/vipera_russelli"
      },
      {
        "id": 44,
        "slug": "bungarus",
        "name": "Bungarus",
        "scientificName": "Krait",
        "image": "https://res.cloudinary.com/duibfmcw1/image/upload/v1770197852/Bungarus_bypmqc.png",
        "path": "/zoohub/chordata/bungarus"
      },
      {
        "id": 45,
        "slug": "hydrophis",
        "name": "Hydrophis",
        "scientificName": "Sea snake",
        "image": "https://res.cloudinary.com/duibfmcw1/image/upload/v1770197889/Hydrophis_hyllg4.png",
        "path": "/zoohub/chordata/hydrophis"
      },
      {
        "id": 46,
        "slug": "typhlops",
        "name": "Typhlops",
        "scientificName": "Blind snake",
        "image": "https://res.cloudinary.com/duibfmcw1/image/upload/v1770198061/Typhlops_ctg0fa.png",
        "path": "/zoohub/chordata/typhlops"
      },
      {
        "id": 47,
        "slug": "python",
        "name": "Python",
        "scientificName": "Python",
        "image": "https://res.cloudinary.com/duibfmcw1/image/upload/v1770198037/Python_kvqhuq.png",
        "path": "/zoohub/chordata/python"
      },
      {
        "id": 48,
        "slug": "crocodylus",
        "name": "Crocodylus",
        "scientificName": "Crocodile",
        "image": "https://res.cloudinary.com/duibfmcw1/image/upload/v1770197865/Crocodylus_kw1m5m.png",
        "path": "/zoohub/chordata/crocodylus"
      },
      {
        "id": 49,
        "slug": "gavialis_gangeticus",
        "name": "Gavialis gangeticus",
        "scientificName": "Gharial",
        "image": "https://res.cloudinary.com/duibfmcw1/image/upload/v1770197879/Gavialis_gangeticus_opbcsy.png",
        "path": "/zoohub/chordata/gavialis_gangeticus"
      },
      {
        "id": 50,
        "slug": "alligator",
        "name": "Alligator",
        "scientificName": "Alligator",
        "image": "https://res.cloudinary.com/duibfmcw1/image/upload/v1770197838/Alligator_pbeml9.png",
        "path": "/zoohub/chordata/alligator"
      },
      {
        "id": 51,
        "slug": "ichthyosaurus_communis",
        "name": "Ichthyosaurus communis",
        "scientificName": "Fish lizard",
        "image": "https://res.cloudinary.com/duibfmcw1/image/upload/v1770197886/Ichthyosaurus_communis_%EF%B8%8E_mxckvr.png",
        "path": "/zoohub/chordata/ichthyosaurus"
      },
      {
        "id": 52,
        "slug": "triceratops_horridus",
        "name": "Triceratops horridus",
        "scientificName": "Three-horned face",
        "image": "https://res.cloudinary.com/duibfmcw1/image/upload/v1770198064/Triceratops_horridus_%EF%B8%8E_bvpicd.png",
        "path": "/zoohub/chordata/triceratops"
      },
      {
        "id": 53,
        "slug": "stegosaurus_stenops",
        "name": "Stegosaurus stenops",
        "scientificName": "Roofed lizard",
        "image": "https://res.cloudinary.com/duibfmcw1/image/upload/v1770198051/Stegosaurus_stenops_%EF%B8%8E_au7ji4.png",
        "path": "/zoohub/chordata/stegosaurus"
      },
      {
        "id": 54,
        "slug": "brachiosaurus_altithorax",
        "name": "Brachiosaurus altithorax",
        "scientificName": "Arm lizard",
        "image": "https://res.cloudinary.com/duibfmcw1/image/upload/v1770197841/Brachiosaurus_altithorax_%EF%B8%8E_mouin2.png",
        "path": "/zoohub/chordata/brachiosaurus"
      },
      {
        "id": 55,
        "slug": "tyrannosaurus_rex",
        "name": "Tyrannosaurus rex",
        "scientificName": "Tyrant lizard king",
        "image": "https://res.cloudinary.com/duibfmcw1/image/upload/v1770198067/Tyrannosaurus_rex_%EF%B8%8E_cjrciq.png",
        "path": "/zoohub/chordata/tyrannosaurus"
      },
      {
        "id": 56,
        "slug": "",
        "name": "",
        "scientificName": "",
        "image": "",
        "path": ""
      }
    ]
  },
  {
    "id": "aves",
    "className": "Aves",
    "species": [
      {
        "id": 57,
        "slug": "corvus",
        "name": "Corvus",
        "scientificName": "Crow",
        "image": "media/image1.png",
        "path": "/zoohub/chordata/corvus"
      },
      {
        "id": 58,
        "slug": "columba",
        "name": "Columba",
        "scientificName": "Pigeon",
        "image": "media/image2.png",
        "path": "/zoohub/chordata/columba"
      },
      {
        "id": 59,
        "slug": "psittacula",
        "name": "Psittacula",
        "scientificName": "Parakeet",
        "image": "media/image3.png",
        "path": "/zoohub/chordata/psittacula"
      },
      {
        "id": 60,
        "slug": "pavo_cristatus",
        "name": "Pavo cristatus",
        "scientificName": "Peacock",
        "image": "media/image4.png",
        "path": "/zoohub/chordata/pavo_cristatus"
      },
      {
        "id": 61,
        "slug": "aptenodytes_forsteri",
        "name": "Aptenodytes forsteri",
        "scientificName": "Emperor penguin",
        "image": "media/image5.png",
        "path": "/zoohub/chordata/aptenodytes_forsteri"
      },
      {
        "id": 62,
        "slug": "struthio_camelus",
        "name": "Struthio camelus",
        "scientificName": "Ostrich",
        "image": "media/image6.png",
        "path": "/zoohub/chordata/struthio_camelus"
      },
      {
        "id": 63,
        "slug": "rhea",
        "name": "Rhea",
        "scientificName": "Rhea",
        "image": "media/image7.png",
        "path": "/zoohub/chordata/rhea"
      },
      {
        "id": 64,
        "slug": "dromaius_novaehollandiae",
        "name": "Dromaius novaehollandiae",
        "scientificName": "Emu",
        "image": "media/image8.png",
        "path": "/zoohub/chordata/dromaius_novaehollandiae"
      },
      {
        "id": 65,
        "slug": "apteryx",
        "name": "Apteryx",
        "scientificName": "Kiwi",
        "image": "media/image9.png",
        "path": "/zoohub/chordata/apteryx"
      },
      {
        "id": 66,
        "slug": "casuarius",
        "name": "Casuarius",
        "scientificName": "Cassowary",
        "image": "media/image10.png",
        "path": "/zoohub/chordata/casuarius"
      },
      {
        "id": 67,
        "slug": "neophron",
        "name": "Neophron",
        "scientificName": "Egyptian vulture",
        "image": "media/image11.png",
        "path": "/zoohub/chordata/neophron"
      },
      {
        "id": 68,
        "slug": "passer",
        "name": "Passer",
        "scientificName": "Sparrow",
        "image": "media/image12.png",
        "path": "/zoohub/chordata/passer"
      },
      {
        "id": 69,
        "slug": "gallus_gallus",
        "name": "Gallus gallus",
        "scientificName": "Red jungle fowl",
        "image": "media/image13.png",
        "path": "/zoohub/chordata/gallus_gallus"
      },
      {
        "id": 70,
        "slug": "trochilus_colubris",
        "name": "Trochilus colubris",
        "scientificName": "Ruby-throated hummingbird",
        "image": "media/image14.png",
        "path": "/zoohub/chordata/trochilus_colubris"
      },
      {
        "id": 71,
        "slug": "chalcophaps_indica",
        "name": "Chalcophaps indica",
        "scientificName": "Emerald dove",
        "image": "media/image15.png",
        "path": "/zoohub/chordata/chalcophaps_indica"
      },
      {
        "id": 72,
        "slug": "pitohui_dichrous",
        "name": "Pitohui dichrous",
        "scientificName": "Hooded pitohui",
        "image": "media/image16.png",
        "path": "/zoohub/chordata/pitohui_dichrous"
      }
    ]
  },
  {
    "id": "mammalia",
    "className": "Mammalia",
    "species": [
      {
        "id": 84,
        "slug": "ornithorhynchus_anatinus",
        "name": "Ornithorhynchus anatinus",
        "scientificName": "Platypus",
        "image": "media/image1.png",
        "path": "/zoohub/chordata/ornithorhynchus_anatinus"
      },
      {
        "id": 85,
        "slug": "echidna",
        "name": "Echidna",
        "scientificName": "Spiny anteater",
        "image": "media/image2.png",
        "path": "/zoohub/chordata/echidna"
      },
      {
        "id": 86,
        "slug": "antechinus_flavipes",
        "name": "Antechinus flavipes",
        "scientificName": "Yellow-footed antechinus",
        "image": "media/image3.png",
        "path": "/zoohub/chordata/antechinus_flavipes"
      },
      {
        "id": 87,
        "slug": "macropus",
        "name": "Macropus",
        "scientificName": "Kangaroo",
        "image": "media/image4.png",
        "path": "/zoohub/chordata/macropus"
      },
      {
        "id": 88,
        "slug": "phascolarctos_cinereus",
        "name": "Phascolarctos cinereus",
        "scientificName": "Koala",
        "image": "media/image5.png",
        "path": "/zoohub/chordata/phascolarctos_cinereus"
      },
      {
        "id": 89,
        "slug": "vombatus",
        "name": "Vombatus",
        "scientificName": "Wombat",
        "image": "media/image6.png",
        "path": "/zoohub/chordata/vombatus"
      },
      {
        "id": 90,
        "slug": "perameles",
        "name": "Perameles",
        "scientificName": "Bandicoot",
        "image": "media/image7.png",
        "path": "/zoohub/chordata/perameles"
      },
      {
        "id": 91,
        "slug": "petaurus_breviceps",
        "name": "Petaurus breviceps",
        "scientificName": "Sugar glider",
        "image": "media/image8.png",
        "path": "/zoohub/chordata/petaurus_breviceps"
      },
      {
        "id": 92,
        "slug": "notoryctes",
        "name": "Notoryctes",
        "scientificName": "Marsupial mole",
        "image": "media/image9.png",
        "path": "/zoohub/chordata/notoryctes"
      },
      {
        "id": 93,
        "slug": "didelphis_marsupialis",
        "name": "Didelphis marsupialis",
        "scientificName": "Common opossum",
        "image": "media/image10.png",
        "path": "/zoohub/chordata/didelphis_marsupialis"
      },
      {
        "id": 94,
        "slug": "myrmecobius_fasciatus",
        "name": "Myrmecobius fasciatus",
        "scientificName": "Numbat",
        "image": "media/image11.png",
        "path": "/zoohub/chordata/myrmecobius_fasciatus"
      },
      {
        "id": 95,
        "slug": "thylacinus_cynocephalus",
        "name": "Thylacinus cynocephalus",
        "scientificName": "Tasmanian tiger",
        "image": "media/image12.png",
        "path": "/zoohub/chordata/thylacinus_cynocephalus"
      },
      {
        "id": 96,
        "slug": "spilocuscus_maculatus",
        "name": "Spilocuscus maculatus",
        "scientificName": "Spotted cuscus",
        "image": "media/image13.png",
        "path": "/zoohub/chordata/spilocuscus_maculatus"
      },
      {
        "id": 97,
        "slug": "dasyurus_maculatus",
        "name": "Dasyurus maculatus",
        "scientificName": "Spotted-tail quoll",
        "image": "media/image14.png",
        "path": "/zoohub/chordata/dasyurus_maculatus"
      }
    ]
  }
]